openmargin/auxiliary.py
openmargin/example.py
openmargin/init.py
openmargin/risk.py
openmargin-0.0.7.dist-info/METADATA
openmargin-0.0.7.dist-info/WHEEL
openmargin-0.0.7.dist-info/licenses/LICENSE
openmargin-0.0.7.dist-info/RECORD
