Metadata-Version: 2.3
Name: openmargin
Version: 0.0.7
Summary: Arrow Markets repository for calculation margin requirements for crypto option portfolios.
Project-URL: Homepage, https://github.com/Arrow-Markets-Research/openmargin
Author-email: Arrow Markets Research <ata@subharmonic.tech>
License: GNU GENERAL PUBLIC LICENSE
License-File: LICENSE
Classifier: License :: OSI Approved :: GNU General Public License v3 or later (GPLv3+)
Classifier: Operating System :: OS Independent
Classifier: Programming Language :: Python :: 3
Requires-Python: >=3.8
Requires-Dist: historic-crypto>=0.1
Requires-Dist: numpy>=1.23
Requires-Dist: pandas==1.5.3
Requires-Dist: requests>=2.31
Requires-Dist: scipy>=1.10
